RegChat/__init__.py
RegChat/analysis.py
RegChat/model.py
RegChat/utils.py
RegChat-0.0.7.dist-info/LICENSE
RegChat-0.0.7.dist-info/METADATA
RegChat-0.0.7.dist-info/WHEEL
RegChat-0.0.7.dist-info/top_level.txt
RegChat-0.0.7.dist-info/RECORD
