Metadata-Version: 2.1
Name: RegChat
Version: 0.0.7
Summary: Inferring intercellular and intracellular communications from single cell and spatial multi-omics data using RegChat
Home-page: https://github.com/lhzhanglabtools/RegChat
Author: Lihua Zhang
Author-email: zhanglh@whu.edu.cn
License: MIT
License-File: LICENSE
Requires-Dist: requests
